astral_projection.py
astral_projection-0.1.1.dist-info/WHEEL
astral_projection-0.1.1.dist-info/METADATA
astral_projection-0.1.1.dist-info/RECORD
