Metadata-Version: 2.1
Name: astral-projection
Version: 0.1.1
Summary: Run code inside a context manager on a remote machine
Home-page: https://github.com/L3viathan/astral-projection
Author: L3viathan
Author-email: git@l3vi.de
Requires-Python: >=3.8,<4.0
Classifier: Programming Language :: Python :: 3
Classifier: Programming Language :: Python :: 3.10
Classifier: Programming Language :: Python :: 3.8
Classifier: Programming Language :: Python :: 3.9
Requires-Dist: colorful (>=0.5.4,<0.6.0)
Requires-Dist: dont (>=0.1.0,<0.2.0)
Project-URL: Repository, https://github.com/L3viathan/astral-projection
